sopel_subcmd/__init__.py
sopel_subcmd/dispatch.py
sopel_subcmd-1.0.0.dist-info/LICENSE
sopel_subcmd-1.0.0.dist-info/METADATA
sopel_subcmd-1.0.0.dist-info/WHEEL
sopel_subcmd-1.0.0.dist-info/entry_points.txt
sopel_subcmd-1.0.0.dist-info/top_level.txt
sopel_subcmd-1.0.0.dist-info/RECORD
